{
    "title": "gd1984-07-04.109942.beyer-senn-daweez.D5scott.flac16",
    "venue": "Five Seasons Center",
    "year": 1984,
    "month": 7,
    "day": 4,
    "songs": [
        {
            "song": "",
            "order": 1,
            "length": 142,
            "ogg": "https://archive.org/download/gd1984-07-04.109942.beyer-senn-daweez.D5scott.flac16/d1t01.ogg",
            "mp3": "https://archive.org/download/gd1984-07-04.109942.beyer-senn-daweez.D5scott.flac16/d1t01.mp3"
        },
        {
            "song": "Feel Like A Stranger",
            "order": 2,
            "length": 530,
            "ogg": "https://archive.org/download/gd1984-07-04.109942.beyer-senn-daweez.D5scott.flac16/d1t02.ogg",
            "mp3": "https://archive.org/download/gd1984-07-04.109942.beyer-senn-daweez.D5scott.flac16/d1t02.mp3"
        },
        {
            "song": "Friend Of The Devil",
            "order": 3,
            "length": 514,
            "ogg": "https://archive.org/download/gd1984-07-04.109942.beyer-senn-daweez.D5scott.flac16/d1t03.ogg",
            "mp3": "https://archive.org/download/gd1984-07-04.109942.beyer-senn-daweez.D5scott.flac16/d1t03.mp3"
        },
        {
            "song": "C C Rider",
            "order": 4,
            "length": 511,
            "ogg": "https://archive.org/download/gd1984-07-04.109942.beyer-senn-daweez.D5scott.flac16/d1t04.ogg",
            "mp3": "https://archive.org/download/gd1984-07-04.109942.beyer-senn-daweez.D5scott.flac16/d1t04.mp3"
        },
        {
            "song": "Cumberland Blues",
            "order": 5,
            "length": 382,
            "ogg": "https://archive.org/download/gd1984-07-04.109942.beyer-senn-daweez.D5scott.flac16/d1t05.ogg",
            "mp3": "https://archive.org/download/gd1984-07-04.109942.beyer-senn-daweez.D5scott.flac16/d1t05.mp3"
        },
        {
            "song": "Beat It On Down The Line",
            "order": 6,
            "length": 236,
            "ogg": "https://archive.org/download/gd1984-07-04.109942.beyer-senn-daweez.D5scott.flac16/d1t06.ogg",
            "mp3": "https://archive.org/download/gd1984-07-04.109942.beyer-senn-daweez.D5scott.flac16/d1t06.mp3"
        },
        {
            "song": "Row Jimmy",
            "order": 7,
            "length": 691,
            "ogg": "https://archive.org/download/gd1984-07-04.109942.beyer-senn-daweez.D5scott.flac16/d1t07.ogg",
            "mp3": "https://archive.org/download/gd1984-07-04.109942.beyer-senn-daweez.D5scott.flac16/d1t07.mp3"
        },
        {
            "song": "Hell In A Bucket",
            "order": 8,
            "length": 434,
            "ogg": "https://archive.org/download/gd1984-07-04.109942.beyer-senn-daweez.D5scott.flac16/d1t08.ogg",
            "mp3": "https://archive.org/download/gd1984-07-04.109942.beyer-senn-daweez.D5scott.flac16/d1t08.mp3"
        },
        {
            "song": "Don't Ease Me In",
            "order": 9,
            "length": 223,
            "ogg": "https://archive.org/download/gd1984-07-04.109942.beyer-senn-daweez.D5scott.flac16/d1t09.ogg",
            "mp3": "https://archive.org/download/gd1984-07-04.109942.beyer-senn-daweez.D5scott.flac16/d1t09.mp3"
        },
        {
            "song": "",
            "order": 10,
            "length": 60,
            "ogg": "https://archive.org/download/gd1984-07-04.109942.beyer-senn-daweez.D5scott.flac16/d2t01.ogg",
            "mp3": "https://archive.org/download/gd1984-07-04.109942.beyer-senn-daweez.D5scott.flac16/d2t01.mp3"
        },
        {
            "song": "Help On The Way",
            "order": 11,
            "length": 211,
            "ogg": "https://archive.org/download/gd1984-07-04.109942.beyer-senn-daweez.D5scott.flac16/d2t02.ogg",
            "mp3": "https://archive.org/download/gd1984-07-04.109942.beyer-senn-daweez.D5scott.flac16/d2t02.mp3"
        },
        {
            "song": "Slipknot!",
            "order": 12,
            "length": 393,
            "ogg": "https://archive.org/download/gd1984-07-04.109942.beyer-senn-daweez.D5scott.flac16/d2t03.ogg",
            "mp3": "https://archive.org/download/gd1984-07-04.109942.beyer-senn-daweez.D5scott.flac16/d2t03.mp3"
        },
        {
            "song": "Franklin's Tower",
            "order": 13,
            "length": 609,
            "ogg": "https://archive.org/download/gd1984-07-04.109942.beyer-senn-daweez.D5scott.flac16/d2t04.ogg",
            "mp3": "https://archive.org/download/gd1984-07-04.109942.beyer-senn-daweez.D5scott.flac16/d2t04.mp3"
        },
        {
            "song": "Far From Me",
            "order": 14,
            "length": 292,
            "ogg": "https://archive.org/download/gd1984-07-04.109942.beyer-senn-daweez.D5scott.flac16/d2t05.ogg",
            "mp3": "https://archive.org/download/gd1984-07-04.109942.beyer-senn-daweez.D5scott.flac16/d2t05.mp3"
        },
        {
            "song": "Estimated Prophet",
            "order": 15,
            "length": 780,
            "ogg": "https://archive.org/download/gd1984-07-04.109942.beyer-senn-daweez.D5scott.flac16/d2t06.ogg",
            "mp3": "https://archive.org/download/gd1984-07-04.109942.beyer-senn-daweez.D5scott.flac16/d2t06.mp3"
        },
        {
            "song": "He's Gone **",
            "order": 16,
            "length": 830,
            "ogg": "https://archive.org/download/gd1984-07-04.109942.beyer-senn-daweez.D5scott.flac16/d2t07.ogg",
            "mp3": "https://archive.org/download/gd1984-07-04.109942.beyer-senn-daweez.D5scott.flac16/d2t07.mp3"
        },
        {
            "song": "Drums",
            "order": 17,
            "length": 186,
            "ogg": "https://archive.org/download/gd1984-07-04.109942.beyer-senn-daweez.D5scott.flac16/d2t08.ogg",
            "mp3": "https://archive.org/download/gd1984-07-04.109942.beyer-senn-daweez.D5scott.flac16/d2t08.mp3"
        },
        {
            "song": "Space",
            "order": 18,
            "length": 502,
            "ogg": "https://archive.org/download/gd1984-07-04.109942.beyer-senn-daweez.D5scott.flac16/d3t01.ogg",
            "mp3": "https://archive.org/download/gd1984-07-04.109942.beyer-senn-daweez.D5scott.flac16/d3t01.mp3"
        },
        {
            "song": "Truckin'",
            "order": 19,
            "length": 448,
            "ogg": "https://archive.org/download/gd1984-07-04.109942.beyer-senn-daweez.D5scott.flac16/d3t02.ogg",
            "mp3": "https://archive.org/download/gd1984-07-04.109942.beyer-senn-daweez.D5scott.flac16/d3t02.mp3"
        },
        {
            "song": "Wharf Rat",
            "order": 20,
            "length": 560,
            "ogg": "https://archive.org/download/gd1984-07-04.109942.beyer-senn-daweez.D5scott.flac16/d3t03.ogg",
            "mp3": "https://archive.org/download/gd1984-07-04.109942.beyer-senn-daweez.D5scott.flac16/d3t03.mp3"
        },
        {
            "song": "Around & Around",
            "order": 21,
            "length": 230,
            "ogg": "https://archive.org/download/gd1984-07-04.109942.beyer-senn-daweez.D5scott.flac16/d3t04.ogg",
            "mp3": "https://archive.org/download/gd1984-07-04.109942.beyer-senn-daweez.D5scott.flac16/d3t04.mp3"
        },
        {
            "song": "Good Lovin'",
            "order": 22,
            "length": 469,
            "ogg": "https://archive.org/download/gd1984-07-04.109942.beyer-senn-daweez.D5scott.flac16/d3t05.ogg",
            "mp3": "https://archive.org/download/gd1984-07-04.109942.beyer-senn-daweez.D5scott.flac16/d3t05.mp3"
        },
        {
            "song": "U.S. Blues",
            "order": 23,
            "length": 329,
            "ogg": "https://archive.org/download/gd1984-07-04.109942.beyer-senn-daweez.D5scott.flac16/d3t06.ogg",
            "mp3": "https://archive.org/download/gd1984-07-04.109942.beyer-senn-daweez.D5scott.flac16/d3t06.mp3"
        }
    ]
}