{
    "title": "gd1990-04-02.137933.dbx.hale.flac16",
    "venue": "The Omni",
    "year": 1990,
    "month": 4,
    "day": 2,
    "songs": [
        {
            "song": "Tuning>",
            "order": 1,
            "length": 57,
            "ogg": "https://archive.org/download/gd1990-04-02.137933.dbx.hale.flac16/gd90-04-02.dbx.hale.flac16-d1t01.ogg",
            "mp3": "https://archive.org/download/gd1990-04-02.137933.dbx.hale.flac16/gd90-04-02.dbx.hale.flac16-d1t01.mp3"
        },
        {
            "song": "Feel Like A Stranger",
            "order": 2,
            "length": 562,
            "ogg": "https://archive.org/download/gd1990-04-02.137933.dbx.hale.flac16/gd90-04-02.dbx.hale.flac16-d1t02.ogg",
            "mp3": "https://archive.org/download/gd1990-04-02.137933.dbx.hale.flac16/gd90-04-02.dbx.hale.flac16-d1t02.mp3"
        },
        {
            "song": "Mississippi Half Step>",
            "order": 3,
            "length": 452,
            "ogg": "https://archive.org/download/gd1990-04-02.137933.dbx.hale.flac16/gd90-04-02.dbx.hale.flac16-d1t03.ogg",
            "mp3": "https://archive.org/download/gd1990-04-02.137933.dbx.hale.flac16/gd90-04-02.dbx.hale.flac16-d1t03.mp3"
        },
        {
            "song": "The Weight",
            "order": 4,
            "length": 414,
            "ogg": "https://archive.org/download/gd1990-04-02.137933.dbx.hale.flac16/gd90-04-02.dbx.hale.flac16-d1t04.ogg",
            "mp3": "https://archive.org/download/gd1990-04-02.137933.dbx.hale.flac16/gd90-04-02.dbx.hale.flac16-d1t04.mp3"
        },
        {
            "song": "Queen Jane Approximately",
            "order": 5,
            "length": 415,
            "ogg": "https://archive.org/download/gd1990-04-02.137933.dbx.hale.flac16/gd90-04-02.dbx.hale.flac16-d1t05.ogg",
            "mp3": "https://archive.org/download/gd1990-04-02.137933.dbx.hale.flac16/gd90-04-02.dbx.hale.flac16-d1t05.mp3"
        },
        {
            "song": "Easy To Love You",
            "order": 6,
            "length": 350,
            "ogg": "https://archive.org/download/gd1990-04-02.137933.dbx.hale.flac16/gd90-04-02.dbx.hale.flac16-d1t06.ogg",
            "mp3": "https://archive.org/download/gd1990-04-02.137933.dbx.hale.flac16/gd90-04-02.dbx.hale.flac16-d1t06.mp3"
        },
        {
            "song": "Brown Eyed Women",
            "order": 7,
            "length": 401,
            "ogg": "https://archive.org/download/gd1990-04-02.137933.dbx.hale.flac16/gd90-04-02.dbx.hale.flac16-d1t07.ogg",
            "mp3": "https://archive.org/download/gd1990-04-02.137933.dbx.hale.flac16/gd90-04-02.dbx.hale.flac16-d1t07.mp3"
        },
        {
            "song": "Let It Grow",
            "order": 8,
            "length": 780,
            "ogg": "https://archive.org/download/gd1990-04-02.137933.dbx.hale.flac16/gd90-04-02.dbx.hale.flac16-d1t08.ogg",
            "mp3": "https://archive.org/download/gd1990-04-02.137933.dbx.hale.flac16/gd90-04-02.dbx.hale.flac16-d1t08.mp3"
        },
        {
            "song": "Tuning>",
            "order": 9,
            "length": 51,
            "ogg": "https://archive.org/download/gd1990-04-02.137933.dbx.hale.flac16/gd90-04-02.dbx.hale.flac16-d2t01.ogg",
            "mp3": "https://archive.org/download/gd1990-04-02.137933.dbx.hale.flac16/gd90-04-02.dbx.hale.flac16-d2t01.mp3"
        },
        {
            "song": "Foolish Heart>",
            "order": 10,
            "length": 572,
            "ogg": "https://archive.org/download/gd1990-04-02.137933.dbx.hale.flac16/gd90-04-02.dbx.hale.flac16-d2t02.ogg",
            "mp3": "https://archive.org/download/gd1990-04-02.137933.dbx.hale.flac16/gd90-04-02.dbx.hale.flac16-d2t02.mp3"
        },
        {
            "song": "Looks Like Rain>",
            "order": 11,
            "length": 521,
            "ogg": "https://archive.org/download/gd1990-04-02.137933.dbx.hale.flac16/gd90-04-02.dbx.hale.flac16-d2t03.ogg",
            "mp3": "https://archive.org/download/gd1990-04-02.137933.dbx.hale.flac16/gd90-04-02.dbx.hale.flac16-d2t03.mp3"
        },
        {
            "song": "He's Gone>",
            "order": 12,
            "length": 555,
            "ogg": "https://archive.org/download/gd1990-04-02.137933.dbx.hale.flac16/gd90-04-02.dbx.hale.flac16-d2t04.ogg",
            "mp3": "https://archive.org/download/gd1990-04-02.137933.dbx.hale.flac16/gd90-04-02.dbx.hale.flac16-d2t04.mp3"
        },
        {
            "song": "The Last Time>",
            "order": 13,
            "length": 350,
            "ogg": "https://archive.org/download/gd1990-04-02.137933.dbx.hale.flac16/gd90-04-02.dbx.hale.flac16-d2t05.ogg",
            "mp3": "https://archive.org/download/gd1990-04-02.137933.dbx.hale.flac16/gd90-04-02.dbx.hale.flac16-d2t05.mp3"
        },
        {
            "song": "Drums>",
            "order": 14,
            "length": 655,
            "ogg": "https://archive.org/download/gd1990-04-02.137933.dbx.hale.flac16/gd90-04-02.dbx.hale.flac16-d2t06.ogg",
            "mp3": "https://archive.org/download/gd1990-04-02.137933.dbx.hale.flac16/gd90-04-02.dbx.hale.flac16-d2t06.mp3"
        },
        {
            "song": "Space>",
            "order": 15,
            "length": 428,
            "ogg": "https://archive.org/download/gd1990-04-02.137933.dbx.hale.flac16/gd90-04-02.dbx.hale.flac16-d2t07.ogg",
            "mp3": "https://archive.org/download/gd1990-04-02.137933.dbx.hale.flac16/gd90-04-02.dbx.hale.flac16-d2t07.mp3"
        },
        {
            "song": "The Other One>",
            "order": 16,
            "length": 491,
            "ogg": "https://archive.org/download/gd1990-04-02.137933.dbx.hale.flac16/gd90-04-02.dbx.hale.flac16-d3t01.ogg",
            "mp3": "https://archive.org/download/gd1990-04-02.137933.dbx.hale.flac16/gd90-04-02.dbx.hale.flac16-d3t01.mp3"
        },
        {
            "song": "Death Don't Have No Mercy*>",
            "order": 17,
            "length": 472,
            "ogg": "https://archive.org/download/gd1990-04-02.137933.dbx.hale.flac16/gd90-04-02.dbx.hale.flac16-d3t02.ogg",
            "mp3": "https://archive.org/download/gd1990-04-02.137933.dbx.hale.flac16/gd90-04-02.dbx.hale.flac16-d3t02.mp3"
        },
        {
            "song": "Around & Around>",
            "order": 18,
            "length": 229,
            "ogg": "https://archive.org/download/gd1990-04-02.137933.dbx.hale.flac16/gd90-04-02.dbx.hale.flac16-d3t03.ogg",
            "mp3": "https://archive.org/download/gd1990-04-02.137933.dbx.hale.flac16/gd90-04-02.dbx.hale.flac16-d3t03.mp3"
        },
        {
            "song": "Good Lovin'",
            "order": 19,
            "length": 400,
            "ogg": "https://archive.org/download/gd1990-04-02.137933.dbx.hale.flac16/gd90-04-02.dbx.hale.flac16-d3t04.ogg",
            "mp3": "https://archive.org/download/gd1990-04-02.137933.dbx.hale.flac16/gd90-04-02.dbx.hale.flac16-d3t04.mp3"
        },
        {
            "song": "Black Muddy River",
            "order": 20,
            "length": 451,
            "ogg": "https://archive.org/download/gd1990-04-02.137933.dbx.hale.flac16/gd90-04-02.dbx.hale.flac16-d3t05.ogg",
            "mp3": "https://archive.org/download/gd1990-04-02.137933.dbx.hale.flac16/gd90-04-02.dbx.hale.flac16-d3t05.mp3"
        }
    ]
}