{
    "title": "gd1985-03-10.senn.pa-deli.mike.83219.flac16",
    "venue": "Berkeley Community Theatre",
    "year": 1985,
    "month": 3,
    "day": 10,
    "songs": [
        {
            "song": "Feel Like A Stranger",
            "order": 1,
            "length": 544,
            "ogg": "https://archive.org/download/gd1985-03-10.senn.pa-deli.mike.83219.flac16/gd1985-03-10d1t01.ogg",
            "mp3": "https://archive.org/download/gd1985-03-10.senn.pa-deli.mike.83219.flac16/gd1985-03-10d1t01.mp3"
        },
        {
            "song": "Peggy-O",
            "order": 2,
            "length": 405,
            "ogg": "https://archive.org/download/gd1985-03-10.senn.pa-deli.mike.83219.flac16/gd1985-03-10d1t02.ogg",
            "mp3": "https://archive.org/download/gd1985-03-10.senn.pa-deli.mike.83219.flac16/gd1985-03-10d1t02.mp3"
        },
        {
            "song": "CC Rider",
            "order": 3,
            "length": 494,
            "ogg": "https://archive.org/download/gd1985-03-10.senn.pa-deli.mike.83219.flac16/gd1985-03-10d1t03.ogg",
            "mp3": "https://archive.org/download/gd1985-03-10.senn.pa-deli.mike.83219.flac16/gd1985-03-10d1t03.mp3"
        },
        {
            "song": "Bird Song",
            "order": 4,
            "length": 676,
            "ogg": "https://archive.org/download/gd1985-03-10.senn.pa-deli.mike.83219.flac16/gd1985-03-10d1t04.ogg",
            "mp3": "https://archive.org/download/gd1985-03-10.senn.pa-deli.mike.83219.flac16/gd1985-03-10d1t04.mp3"
        },
        {
            "song": "Hell In A Bucket",
            "order": 5,
            "length": 406,
            "ogg": "https://archive.org/download/gd1985-03-10.senn.pa-deli.mike.83219.flac16/gd1985-03-10d1t05.ogg",
            "mp3": "https://archive.org/download/gd1985-03-10.senn.pa-deli.mike.83219.flac16/gd1985-03-10d1t05.mp3"
        },
        {
            "song": "Big Railroad BLues",
            "order": 6,
            "length": 356,
            "ogg": "https://archive.org/download/gd1985-03-10.senn.pa-deli.mike.83219.flac16/gd1985-03-10d1t06.ogg",
            "mp3": "https://archive.org/download/gd1985-03-10.senn.pa-deli.mike.83219.flac16/gd1985-03-10d1t06.mp3"
        },
        {
            "song": "Samson and Delilah",
            "order": 7,
            "length": 499,
            "ogg": "https://archive.org/download/gd1985-03-10.senn.pa-deli.mike.83219.flac16/gd1985-03-10d2t01.ogg",
            "mp3": "https://archive.org/download/gd1985-03-10.senn.pa-deli.mike.83219.flac16/gd1985-03-10d2t01.mp3"
        },
        {
            "song": "Terrapin Station",
            "order": 8,
            "length": 756,
            "ogg": "https://archive.org/download/gd1985-03-10.senn.pa-deli.mike.83219.flac16/gd1985-03-10d2t02.ogg",
            "mp3": "https://archive.org/download/gd1985-03-10.senn.pa-deli.mike.83219.flac16/gd1985-03-10d2t02.mp3"
        },
        {
            "song": "Truckin'",
            "order": 9,
            "length": 456,
            "ogg": "https://archive.org/download/gd1985-03-10.senn.pa-deli.mike.83219.flac16/gd1985-03-10d2t03.ogg",
            "mp3": "https://archive.org/download/gd1985-03-10.senn.pa-deli.mike.83219.flac16/gd1985-03-10d2t03.mp3"
        },
        {
            "song": "Smokestack Lightening",
            "order": 10,
            "length": 278,
            "ogg": "https://archive.org/download/gd1985-03-10.senn.pa-deli.mike.83219.flac16/gd1985-03-10d2t04.ogg",
            "mp3": "https://archive.org/download/gd1985-03-10.senn.pa-deli.mike.83219.flac16/gd1985-03-10d2t04.mp3"
        },
        {
            "song": "Jam",
            "order": 11,
            "length": 533,
            "ogg": "https://archive.org/download/gd1985-03-10.senn.pa-deli.mike.83219.flac16/gd1985-03-10d2t05.ogg",
            "mp3": "https://archive.org/download/gd1985-03-10.senn.pa-deli.mike.83219.flac16/gd1985-03-10d2t05.mp3"
        },
        {
            "song": "Drums",
            "order": 12,
            "length": 318,
            "ogg": "https://archive.org/download/gd1985-03-10.senn.pa-deli.mike.83219.flac16/gd1985-03-10d2t06.ogg",
            "mp3": "https://archive.org/download/gd1985-03-10.senn.pa-deli.mike.83219.flac16/gd1985-03-10d2t06.mp3"
        },
        {
            "song": "Drums",
            "order": 13,
            "length": 240,
            "ogg": "https://archive.org/download/gd1985-03-10.senn.pa-deli.mike.83219.flac16/gd1985-03-10d3t01.ogg",
            "mp3": "https://archive.org/download/gd1985-03-10.senn.pa-deli.mike.83219.flac16/gd1985-03-10d3t01.mp3"
        },
        {
            "song": "Space",
            "order": 14,
            "length": 548,
            "ogg": "https://archive.org/download/gd1985-03-10.senn.pa-deli.mike.83219.flac16/gd1985-03-10d3t02.ogg",
            "mp3": "https://archive.org/download/gd1985-03-10.senn.pa-deli.mike.83219.flac16/gd1985-03-10d3t02.mp3"
        },
        {
            "song": "Stella Blue",
            "order": 15,
            "length": 597,
            "ogg": "https://archive.org/download/gd1985-03-10.senn.pa-deli.mike.83219.flac16/gd1985-03-10d3t03.ogg",
            "mp3": "https://archive.org/download/gd1985-03-10.senn.pa-deli.mike.83219.flac16/gd1985-03-10d3t03.mp3"
        },
        {
            "song": "Goin' Down The Road Feeling Bad",
            "order": 16,
            "length": 311,
            "ogg": "https://archive.org/download/gd1985-03-10.senn.pa-deli.mike.83219.flac16/gd1985-03-10d3t04.ogg",
            "mp3": "https://archive.org/download/gd1985-03-10.senn.pa-deli.mike.83219.flac16/gd1985-03-10d3t04.mp3"
        },
        {
            "song": "Around and Around",
            "order": 17,
            "length": 233,
            "ogg": "https://archive.org/download/gd1985-03-10.senn.pa-deli.mike.83219.flac16/gd1985-03-10d3t05.ogg",
            "mp3": "https://archive.org/download/gd1985-03-10.senn.pa-deli.mike.83219.flac16/gd1985-03-10d3t05.mp3"
        },
        {
            "song": "Johnny B. Goode",
            "order": 18,
            "length": 254,
            "ogg": "https://archive.org/download/gd1985-03-10.senn.pa-deli.mike.83219.flac16/gd1985-03-10d3t06.ogg",
            "mp3": "https://archive.org/download/gd1985-03-10.senn.pa-deli.mike.83219.flac16/gd1985-03-10d3t06.mp3"
        },
        {
            "song": "Day Job",
            "order": 19,
            "length": 290,
            "ogg": "https://archive.org/download/gd1985-03-10.senn.pa-deli.mike.83219.flac16/gd1985-03-10d3t07.ogg",
            "mp3": "https://archive.org/download/gd1985-03-10.senn.pa-deli.mike.83219.flac16/gd1985-03-10d3t07.mp3"
        }
    ]
}