{
    "title": "gd1994-09-18.147727.aud.unknown.ebel.flac16",
    "venue": "Shoreline Amphitheatre",
    "year": 1994,
    "month": 9,
    "day": 18,
    "songs": [
        {
            "song": "Touch Of Grey",
            "order": 1,
            "length": 420,
            "ogg": "https://archive.org/download/gd1994-09-18.147727.aud.unknown.ebel.flac16/01%20Touch%20Of%20Grey.ogg",
            "mp3": "https://archive.org/download/gd1994-09-18.147727.aud.unknown.ebel.flac16/01%20Touch%20Of%20Grey.mp3"
        },
        {
            "song": "Greatest Story Ever Told",
            "order": 2,
            "length": 257,
            "ogg": "https://archive.org/download/gd1994-09-18.147727.aud.unknown.ebel.flac16/02%20Greatest%20Story%20Ever%20Told.ogg",
            "mp3": "https://archive.org/download/gd1994-09-18.147727.aud.unknown.ebel.flac16/02%20Greatest%20Story%20Ever%20Told.mp3"
        },
        {
            "song": "Jack-A-Roe",
            "order": 3,
            "length": 346,
            "ogg": "https://archive.org/download/gd1994-09-18.147727.aud.unknown.ebel.flac16/03%20Jack-A_Roe.ogg",
            "mp3": "https://archive.org/download/gd1994-09-18.147727.aud.unknown.ebel.flac16/03%20Jack-A_Roe.mp3"
        },
        {
            "song": "Little Red Rooster",
            "order": 4,
            "length": 516,
            "ogg": "https://archive.org/download/gd1994-09-18.147727.aud.unknown.ebel.flac16/04%20Little%20Red%20Rooster.ogg",
            "mp3": "https://archive.org/download/gd1994-09-18.147727.aud.unknown.ebel.flac16/04%20Little%20Red%20Rooster.mp3"
        },
        {
            "song": "Tennessee Jed",
            "order": 5,
            "length": 484,
            "ogg": "https://archive.org/download/gd1994-09-18.147727.aud.unknown.ebel.flac16/05%20Tennessee%20Jed.ogg",
            "mp3": "https://archive.org/download/gd1994-09-18.147727.aud.unknown.ebel.flac16/05%20Tennessee%20Jed.mp3"
        },
        {
            "song": "El Paso",
            "order": 6,
            "length": 388,
            "ogg": "https://archive.org/download/gd1994-09-18.147727.aud.unknown.ebel.flac16/06%20El%20Paso.ogg",
            "mp3": "https://archive.org/download/gd1994-09-18.147727.aud.unknown.ebel.flac16/06%20El%20Paso.mp3"
        },
        {
            "song": "Brown-Eyed Women",
            "order": 7,
            "length": 347,
            "ogg": "https://archive.org/download/gd1994-09-18.147727.aud.unknown.ebel.flac16/07%20Brown-Eyed%20Women.ogg",
            "mp3": "https://archive.org/download/gd1994-09-18.147727.aud.unknown.ebel.flac16/07%20Brown-Eyed%20Women.mp3"
        },
        {
            "song": "Music Never Stopped",
            "order": 8,
            "length": 647,
            "ogg": "https://archive.org/download/gd1994-09-18.147727.aud.unknown.ebel.flac16/08%20Music%20Never%20Stopped.ogg",
            "mp3": "https://archive.org/download/gd1994-09-18.147727.aud.unknown.ebel.flac16/08%20Music%20Never%20Stopped.mp3"
        },
        {
            "song": "Iko-Iko",
            "order": 9,
            "length": 674,
            "ogg": "https://archive.org/download/gd1994-09-18.147727.aud.unknown.ebel.flac16/09%20Iko-Iko.ogg",
            "mp3": "https://archive.org/download/gd1994-09-18.147727.aud.unknown.ebel.flac16/09%20Iko-Iko.mp3"
        },
        {
            "song": "Saint Of Circumstance",
            "order": 10,
            "length": 476,
            "ogg": "https://archive.org/download/gd1994-09-18.147727.aud.unknown.ebel.flac16/10%20Saint%20Of%20Circumstance.ogg",
            "mp3": "https://archive.org/download/gd1994-09-18.147727.aud.unknown.ebel.flac16/10%20Saint%20Of%20Circumstance.mp3"
        },
        {
            "song": "Samba In The Rain",
            "order": 11,
            "length": 444,
            "ogg": "https://archive.org/download/gd1994-09-18.147727.aud.unknown.ebel.flac16/11%20Samba%20In%20The%20Rain.ogg",
            "mp3": "https://archive.org/download/gd1994-09-18.147727.aud.unknown.ebel.flac16/11%20Samba%20In%20The%20Rain.mp3"
        },
        {
            "song": "So Many Roads",
            "order": 12,
            "length": 581,
            "ogg": "https://archive.org/download/gd1994-09-18.147727.aud.unknown.ebel.flac16/12%20So%20Many%20Roads.ogg",
            "mp3": "https://archive.org/download/gd1994-09-18.147727.aud.unknown.ebel.flac16/12%20So%20Many%20Roads.mp3"
        },
        {
            "song": "Samson & Delilah",
            "order": 13,
            "length": 432,
            "ogg": "https://archive.org/download/gd1994-09-18.147727.aud.unknown.ebel.flac16/13%20Samson%20%26%20Delilah.ogg",
            "mp3": "https://archive.org/download/gd1994-09-18.147727.aud.unknown.ebel.flac16/13%20Samson%20%26%20Delilah.mp3"
        },
        {
            "song": "Drumz",
            "order": 14,
            "length": 822,
            "ogg": "https://archive.org/download/gd1994-09-18.147727.aud.unknown.ebel.flac16/14%20Drumz.ogg",
            "mp3": "https://archive.org/download/gd1994-09-18.147727.aud.unknown.ebel.flac16/14%20Drumz.mp3"
        },
        {
            "song": "Space",
            "order": 15,
            "length": 578,
            "ogg": "https://archive.org/download/gd1994-09-18.147727.aud.unknown.ebel.flac16/15%20Space.ogg",
            "mp3": "https://archive.org/download/gd1994-09-18.147727.aud.unknown.ebel.flac16/15%20Space.mp3"
        },
        {
            "song": "The Days Between",
            "order": 16,
            "length": 770,
            "ogg": "https://archive.org/download/gd1994-09-18.147727.aud.unknown.ebel.flac16/16%20The%20Days%20Between.ogg",
            "mp3": "https://archive.org/download/gd1994-09-18.147727.aud.unknown.ebel.flac16/16%20The%20Days%20Between.mp3"
        },
        {
            "song": "Throwing Stones",
            "order": 17,
            "length": 535,
            "ogg": "https://archive.org/download/gd1994-09-18.147727.aud.unknown.ebel.flac16/17%20Throwing%20Stones.ogg",
            "mp3": "https://archive.org/download/gd1994-09-18.147727.aud.unknown.ebel.flac16/17%20Throwing%20Stones.mp3"
        },
        {
            "song": "Not Fade Away",
            "order": 18,
            "length": 564,
            "ogg": "https://archive.org/download/gd1994-09-18.147727.aud.unknown.ebel.flac16/18%20Not%20Fade%20Away.ogg",
            "mp3": "https://archive.org/download/gd1994-09-18.147727.aud.unknown.ebel.flac16/18%20Not%20Fade%20Away.mp3"
        },
        {
            "song": "Brokedown Palace",
            "order": 19,
            "length": 304,
            "ogg": "https://archive.org/download/gd1994-09-18.147727.aud.unknown.ebel.flac16/19%20Brokedown%20Palace.ogg",
            "mp3": "https://archive.org/download/gd1994-09-18.147727.aud.unknown.ebel.flac16/19%20Brokedown%20Palace.mp3"
        }
    ]
}