{
    "title": "gd1990-07-12.133957.akg414btl-fob-dantepper.flac16",
    "venue": "Robert F. Kennedy Stadium",
    "year": 1990,
    "month": 7,
    "day": 12,
    "songs": [
        {
            "song": "Let The Good Times Roll",
            "order": 1,
            "length": 322,
            "ogg": "https://archive.org/download/gd1990-07-12.133957.akg414btl-fob-dantepper.flac16/gd1990-07-12_akg414btl_fob_dantepper_d1t01.ogg",
            "mp3": "https://archive.org/download/gd1990-07-12.133957.akg414btl-fob-dantepper.flac16/gd1990-07-12_akg414btl_fob_dantepper_d1t01.mp3"
        },
        {
            "song": "Feel Like A Stranger",
            "order": 2,
            "length": 482,
            "ogg": "https://archive.org/download/gd1990-07-12.133957.akg414btl-fob-dantepper.flac16/gd1990-07-12_akg414btl_fob_dantepper_d1t02.ogg",
            "mp3": "https://archive.org/download/gd1990-07-12.133957.akg414btl-fob-dantepper.flac16/gd1990-07-12_akg414btl_fob_dantepper_d1t02.mp3"
        },
        {
            "song": "Bertha",
            "order": 3,
            "length": 463,
            "ogg": "https://archive.org/download/gd1990-07-12.133957.akg414btl-fob-dantepper.flac16/gd1990-07-12_akg414btl_fob_dantepper_d1t03.ogg",
            "mp3": "https://archive.org/download/gd1990-07-12.133957.akg414btl-fob-dantepper.flac16/gd1990-07-12_akg414btl_fob_dantepper_d1t03.mp3"
        },
        {
            "song": "Just A Little Light",
            "order": 4,
            "length": 333,
            "ogg": "https://archive.org/download/gd1990-07-12.133957.akg414btl-fob-dantepper.flac16/gd1990-07-12_akg414btl_fob_dantepper_d1t04.ogg",
            "mp3": "https://archive.org/download/gd1990-07-12.133957.akg414btl-fob-dantepper.flac16/gd1990-07-12_akg414btl_fob_dantepper_d1t04.mp3"
        },
        {
            "song": "Queen Jane Approximately",
            "order": 5,
            "length": 406,
            "ogg": "https://archive.org/download/gd1990-07-12.133957.akg414btl-fob-dantepper.flac16/gd1990-07-12_akg414btl_fob_dantepper_d1t05.ogg",
            "mp3": "https://archive.org/download/gd1990-07-12.133957.akg414btl-fob-dantepper.flac16/gd1990-07-12_akg414btl_fob_dantepper_d1t05.mp3"
        },
        {
            "song": "Stagger Lee",
            "order": 6,
            "length": 349,
            "ogg": "https://archive.org/download/gd1990-07-12.133957.akg414btl-fob-dantepper.flac16/gd1990-07-12_akg414btl_fob_dantepper_d1t06.ogg",
            "mp3": "https://archive.org/download/gd1990-07-12.133957.akg414btl-fob-dantepper.flac16/gd1990-07-12_akg414btl_fob_dantepper_d1t06.mp3"
        },
        {
            "song": "Cassidy",
            "order": 7,
            "length": 408,
            "ogg": "https://archive.org/download/gd1990-07-12.133957.akg414btl-fob-dantepper.flac16/gd1990-07-12_akg414btl_fob_dantepper_d1t07.ogg",
            "mp3": "https://archive.org/download/gd1990-07-12.133957.akg414btl-fob-dantepper.flac16/gd1990-07-12_akg414btl_fob_dantepper_d1t07.mp3"
        },
        {
            "song": "Tennessee Jed",
            "order": 8,
            "length": 487,
            "ogg": "https://archive.org/download/gd1990-07-12.133957.akg414btl-fob-dantepper.flac16/gd1990-07-12_akg414btl_fob_dantepper_d1t08.ogg",
            "mp3": "https://archive.org/download/gd1990-07-12.133957.akg414btl-fob-dantepper.flac16/gd1990-07-12_akg414btl_fob_dantepper_d1t08.mp3"
        },
        {
            "song": "The Music Never Stopped",
            "order": 9,
            "length": 494,
            "ogg": "https://archive.org/download/gd1990-07-12.133957.akg414btl-fob-dantepper.flac16/gd1990-07-12_akg414btl_fob_dantepper_d1t09.ogg",
            "mp3": "https://archive.org/download/gd1990-07-12.133957.akg414btl-fob-dantepper.flac16/gd1990-07-12_akg414btl_fob_dantepper_d1t09.mp3"
        },
        {
            "song": "Box Of Rain",
            "order": 10,
            "length": 412,
            "ogg": "https://archive.org/download/gd1990-07-12.133957.akg414btl-fob-dantepper.flac16/gd1990-07-12_akg414btl_fob_dantepper_d2t01.ogg",
            "mp3": "https://archive.org/download/gd1990-07-12.133957.akg414btl-fob-dantepper.flac16/gd1990-07-12_akg414btl_fob_dantepper_d2t01.mp3"
        },
        {
            "song": "Victim Or The Crime",
            "order": 11,
            "length": 508,
            "ogg": "https://archive.org/download/gd1990-07-12.133957.akg414btl-fob-dantepper.flac16/gd1990-07-12_akg414btl_fob_dantepper_d2t02.ogg",
            "mp3": "https://archive.org/download/gd1990-07-12.133957.akg414btl-fob-dantepper.flac16/gd1990-07-12_akg414btl_fob_dantepper_d2t02.mp3"
        },
        {
            "song": "Foolish Heart",
            "order": 12,
            "length": 607,
            "ogg": "https://archive.org/download/gd1990-07-12.133957.akg414btl-fob-dantepper.flac16/gd1990-07-12_akg414btl_fob_dantepper_d2t03.ogg",
            "mp3": "https://archive.org/download/gd1990-07-12.133957.akg414btl-fob-dantepper.flac16/gd1990-07-12_akg414btl_fob_dantepper_d2t03.mp3"
        },
        {
            "song": "Dark Star",
            "order": 13,
            "length": 1487,
            "ogg": "https://archive.org/download/gd1990-07-12.133957.akg414btl-fob-dantepper.flac16/gd1990-07-12_akg414btl_fob_dantepper_d2t04.ogg",
            "mp3": "https://archive.org/download/gd1990-07-12.133957.akg414btl-fob-dantepper.flac16/gd1990-07-12_akg414btl_fob_dantepper_d2t04.mp3"
        },
        {
            "song": "Drums",
            "order": 14,
            "length": 652,
            "ogg": "https://archive.org/download/gd1990-07-12.133957.akg414btl-fob-dantepper.flac16/gd1990-07-12_akg414btl_fob_dantepper_d2t05.ogg",
            "mp3": "https://archive.org/download/gd1990-07-12.133957.akg414btl-fob-dantepper.flac16/gd1990-07-12_akg414btl_fob_dantepper_d2t05.mp3"
        },
        {
            "song": "Space",
            "order": 15,
            "length": 916,
            "ogg": "https://archive.org/download/gd1990-07-12.133957.akg414btl-fob-dantepper.flac16/gd1990-07-12_akg414btl_fob_dantepper_d3t01.ogg",
            "mp3": "https://archive.org/download/gd1990-07-12.133957.akg414btl-fob-dantepper.flac16/gd1990-07-12_akg414btl_fob_dantepper_d3t01.mp3"
        },
        {
            "song": "All Along The Watchtower",
            "order": 16,
            "length": 359,
            "ogg": "https://archive.org/download/gd1990-07-12.133957.akg414btl-fob-dantepper.flac16/gd1990-07-12_akg414btl_fob_dantepper_d3t02.ogg",
            "mp3": "https://archive.org/download/gd1990-07-12.133957.akg414btl-fob-dantepper.flac16/gd1990-07-12_akg414btl_fob_dantepper_d3t02.mp3"
        },
        {
            "song": "Dear Mr. Fantasy",
            "order": 17,
            "length": 291,
            "ogg": "https://archive.org/download/gd1990-07-12.133957.akg414btl-fob-dantepper.flac16/gd1990-07-12_akg414btl_fob_dantepper_d3t03.ogg",
            "mp3": "https://archive.org/download/gd1990-07-12.133957.akg414btl-fob-dantepper.flac16/gd1990-07-12_akg414btl_fob_dantepper_d3t03.mp3"
        },
        {
            "song": "Hey Jude Reprise",
            "order": 18,
            "length": 254,
            "ogg": "https://archive.org/download/gd1990-07-12.133957.akg414btl-fob-dantepper.flac16/gd1990-07-12_akg414btl_fob_dantepper_d3t04.ogg",
            "mp3": "https://archive.org/download/gd1990-07-12.133957.akg414btl-fob-dantepper.flac16/gd1990-07-12_akg414btl_fob_dantepper_d3t04.mp3"
        },
        {
            "song": "Touch Of Grey",
            "order": 19,
            "length": 519,
            "ogg": "https://archive.org/download/gd1990-07-12.133957.akg414btl-fob-dantepper.flac16/gd1990-07-12_akg414btl_fob_dantepper_d3t05.ogg",
            "mp3": "https://archive.org/download/gd1990-07-12.133957.akg414btl-fob-dantepper.flac16/gd1990-07-12_akg414btl_fob_dantepper_d3t05.mp3"
        },
        {
            "song": "The Weight",
            "order": 20,
            "length": 439,
            "ogg": "https://archive.org/download/gd1990-07-12.133957.akg414btl-fob-dantepper.flac16/gd1990-07-12_akg414btl_fob_dantepper_d3t06.ogg",
            "mp3": "https://archive.org/download/gd1990-07-12.133957.akg414btl-fob-dantepper.flac16/gd1990-07-12_akg414btl_fob_dantepper_d3t06.mp3"
        }
    ]
}