{
    "title": "gd1979-12-28.128624.naks.mason.flac16",
    "venue": "Oakland Auditorium Arena",
    "year": 1979,
    "month": 12,
    "day": 28,
    "songs": [
        {
            "song": "Tuning",
            "order": 1,
            "length": 73,
            "ogg": "https://archive.org/download/gd1979-12-28.128624.naks.mason.flac16/gd79-12-28.s1t01.ogg",
            "mp3": "https://archive.org/download/gd1979-12-28.128624.naks.mason.flac16/gd79-12-28.s1t01.mp3"
        },
        {
            "song": "Sugaree",
            "order": 2,
            "length": 1006,
            "ogg": "https://archive.org/download/gd1979-12-28.128624.naks.mason.flac16/gd79-12-28.s1t02.ogg",
            "mp3": "https://archive.org/download/gd1979-12-28.128624.naks.mason.flac16/gd79-12-28.s1t02.mp3"
        },
        {
            "song": "Mama Tried >",
            "order": 3,
            "length": 149,
            "ogg": "https://archive.org/download/gd1979-12-28.128624.naks.mason.flac16/gd79-12-28.s1t03.ogg",
            "mp3": "https://archive.org/download/gd1979-12-28.128624.naks.mason.flac16/gd79-12-28.s1t03.mp3"
        },
        {
            "song": "Mexicali Blues",
            "order": 4,
            "length": 350,
            "ogg": "https://archive.org/download/gd1979-12-28.128624.naks.mason.flac16/gd79-12-28.s1t04.ogg",
            "mp3": "https://archive.org/download/gd1979-12-28.128624.naks.mason.flac16/gd79-12-28.s1t04.mp3"
        },
        {
            "song": "Row Jimmy",
            "order": 5,
            "length": 908,
            "ogg": "https://archive.org/download/gd1979-12-28.128624.naks.mason.flac16/gd79-12-28.s1t05.ogg",
            "mp3": "https://archive.org/download/gd1979-12-28.128624.naks.mason.flac16/gd79-12-28.s1t05.mp3"
        },
        {
            "song": "It's All Over Now",
            "order": 6,
            "length": 503,
            "ogg": "https://archive.org/download/gd1979-12-28.128624.naks.mason.flac16/gd79-12-28.s1t06.ogg",
            "mp3": "https://archive.org/download/gd1979-12-28.128624.naks.mason.flac16/gd79-12-28.s1t06.mp3"
        },
        {
            "song": "High Time",
            "order": 7,
            "length": 413,
            "ogg": "https://archive.org/download/gd1979-12-28.128624.naks.mason.flac16/gd79-12-28.s1t07.ogg",
            "mp3": "https://archive.org/download/gd1979-12-28.128624.naks.mason.flac16/gd79-12-28.s1t07.mp3"
        },
        {
            "song": "The Music Never Stopped",
            "order": 8,
            "length": 521,
            "ogg": "https://archive.org/download/gd1979-12-28.128624.naks.mason.flac16/gd79-12-28.s1t08.ogg",
            "mp3": "https://archive.org/download/gd1979-12-28.128624.naks.mason.flac16/gd79-12-28.s1t08.mp3"
        },
        {
            "song": "Tuning",
            "order": 9,
            "length": 99,
            "ogg": "https://archive.org/download/gd1979-12-28.128624.naks.mason.flac16/gd79-12-28.s2t01.ogg",
            "mp3": "https://archive.org/download/gd1979-12-28.128624.naks.mason.flac16/gd79-12-28.s2t01.mp3"
        },
        {
            "song": "Alabama Getaway >",
            "order": 10,
            "length": 403,
            "ogg": "https://archive.org/download/gd1979-12-28.128624.naks.mason.flac16/gd79-12-28.s2t02.ogg",
            "mp3": "https://archive.org/download/gd1979-12-28.128624.naks.mason.flac16/gd79-12-28.s2t02.mp3"
        },
        {
            "song": "Greatest Story Ever Told",
            "order": 11,
            "length": 362,
            "ogg": "https://archive.org/download/gd1979-12-28.128624.naks.mason.flac16/gd79-12-28.s2t03.ogg",
            "mp3": "https://archive.org/download/gd1979-12-28.128624.naks.mason.flac16/gd79-12-28.s2t03.mp3"
        },
        {
            "song": "Terrapin Station >",
            "order": 12,
            "length": 840,
            "ogg": "https://archive.org/download/gd1979-12-28.128624.naks.mason.flac16/gd79-12-28.s2t04.ogg",
            "mp3": "https://archive.org/download/gd1979-12-28.128624.naks.mason.flac16/gd79-12-28.s2t04.mp3"
        },
        {
            "song": "Playin' In The Band >",
            "order": 13,
            "length": 223,
            "ogg": "https://archive.org/download/gd1979-12-28.128624.naks.mason.flac16/gd79-12-28.s2t05.ogg",
            "mp3": "https://archive.org/download/gd1979-12-28.128624.naks.mason.flac16/gd79-12-28.s2t05.mp3"
        },
        {
            "song": "Jam >",
            "order": 14,
            "length": 821,
            "ogg": "https://archive.org/download/gd1979-12-28.128624.naks.mason.flac16/gd79-12-28.s2t06.ogg",
            "mp3": "https://archive.org/download/gd1979-12-28.128624.naks.mason.flac16/gd79-12-28.s2t06.mp3"
        },
        {
            "song": "Drums >",
            "order": 15,
            "length": 456,
            "ogg": "https://archive.org/download/gd1979-12-28.128624.naks.mason.flac16/gd79-12-28.s2t07.ogg",
            "mp3": "https://archive.org/download/gd1979-12-28.128624.naks.mason.flac16/gd79-12-28.s2t07.mp3"
        },
        {
            "song": "Space >",
            "order": 16,
            "length": 148,
            "ogg": "https://archive.org/download/gd1979-12-28.128624.naks.mason.flac16/gd79-12-28.s2t08.ogg",
            "mp3": "https://archive.org/download/gd1979-12-28.128624.naks.mason.flac16/gd79-12-28.s2t08.mp3"
        },
        {
            "song": "Uncle John's Band >",
            "order": 17,
            "length": 580,
            "ogg": "https://archive.org/download/gd1979-12-28.128624.naks.mason.flac16/gd79-12-28.s2t09.ogg",
            "mp3": "https://archive.org/download/gd1979-12-28.128624.naks.mason.flac16/gd79-12-28.s2t09.mp3"
        },
        {
            "song": "I Need A Miracle >",
            "order": 18,
            "length": 244,
            "ogg": "https://archive.org/download/gd1979-12-28.128624.naks.mason.flac16/gd79-12-28.s2t10.ogg",
            "mp3": "https://archive.org/download/gd1979-12-28.128624.naks.mason.flac16/gd79-12-28.s2t10.mp3"
        },
        {
            "song": "Bertha >",
            "order": 19,
            "length": 391,
            "ogg": "https://archive.org/download/gd1979-12-28.128624.naks.mason.flac16/gd79-12-28.s2t11.ogg",
            "mp3": "https://archive.org/download/gd1979-12-28.128624.naks.mason.flac16/gd79-12-28.s2t11.mp3"
        },
        {
            "song": "Good Lovin'",
            "order": 20,
            "length": 433,
            "ogg": "https://archive.org/download/gd1979-12-28.128624.naks.mason.flac16/gd79-12-28.s2t12.ogg",
            "mp3": "https://archive.org/download/gd1979-12-28.128624.naks.mason.flac16/gd79-12-28.s2t12.mp3"
        },
        {
            "song": "Casey Jones",
            "order": 21,
            "length": 326,
            "ogg": "https://archive.org/download/gd1979-12-28.128624.naks.mason.flac16/gd79-12-28.s2t13.ogg",
            "mp3": "https://archive.org/download/gd1979-12-28.128624.naks.mason.flac16/gd79-12-28.s2t13.mp3"
        },
        {
            "song": "One More Saturday Night",
            "order": 22,
            "length": 293,
            "ogg": "https://archive.org/download/gd1979-12-28.128624.naks.mason.flac16/gd79-12-28.s2t14.ogg",
            "mp3": "https://archive.org/download/gd1979-12-28.128624.naks.mason.flac16/gd79-12-28.s2t14.mp3"
        }
    ]
}