{
    "title": "gd1985-06-28.141599.aud.bryant.miller.sirmick.flac2496",
    "venue": "Hershey Park Stadium",
    "year": 1985,
    "month": 6,
    "day": 28,
    "songs": [
        {
            "song": "tuning",
            "order": 1,
            "length": 5,
            "ogg": "https://archive.org/download/gd1985-06-28.141599.aud.bryant.miller.sirmick.flac2496/gd1985-06-28s1t01.ogg",
            "mp3": "https://archive.org/download/gd1985-06-28.141599.aud.bryant.miller.sirmick.flac2496/gd1985-06-28s1t01.mp3"
        },
        {
            "song": "Cold Rain And Snow >",
            "order": 2,
            "length": 54,
            "ogg": "https://archive.org/download/gd1985-06-28.141599.aud.bryant.miller.sirmick.flac2496/gd1985-06-28s1t02.ogg",
            "mp3": "https://archive.org/download/gd1985-06-28.141599.aud.bryant.miller.sirmick.flac2496/gd1985-06-28s1t02.mp3"
        },
        {
            "song": "The Promised Land",
            "order": 3,
            "length": 337,
            "ogg": "https://archive.org/download/gd1985-06-28.141599.aud.bryant.miller.sirmick.flac2496/gd1985-06-28s1t03.ogg",
            "mp3": "https://archive.org/download/gd1985-06-28.141599.aud.bryant.miller.sirmick.flac2496/gd1985-06-28s1t03.mp3"
        },
        {
            "song": "Ramble On Rose",
            "order": 4,
            "length": 255,
            "ogg": "https://archive.org/download/gd1985-06-28.141599.aud.bryant.miller.sirmick.flac2496/gd1985-06-28s1t04.ogg",
            "mp3": "https://archive.org/download/gd1985-06-28.141599.aud.bryant.miller.sirmick.flac2496/gd1985-06-28s1t04.mp3"
        },
        {
            "song": "Down In The Bottom/I Ain't Superstitious",
            "order": 5,
            "length": 407,
            "ogg": "https://archive.org/download/gd1985-06-28.141599.aud.bryant.miller.sirmick.flac2496/gd1985-06-28s1t05.ogg",
            "mp3": "https://archive.org/download/gd1985-06-28.141599.aud.bryant.miller.sirmick.flac2496/gd1985-06-28s1t05.mp3"
        },
        {
            "song": "Bird Song >",
            "order": 6,
            "length": 465,
            "ogg": "https://archive.org/download/gd1985-06-28.141599.aud.bryant.miller.sirmick.flac2496/gd1985-06-28s1t06.ogg",
            "mp3": "https://archive.org/download/gd1985-06-28.141599.aud.bryant.miller.sirmick.flac2496/gd1985-06-28s1t06.mp3"
        },
        {
            "song": "Comes A Time >",
            "order": 7,
            "length": 422,
            "ogg": "https://archive.org/download/gd1985-06-28.141599.aud.bryant.miller.sirmick.flac2496/gd1985-06-28s1t07.ogg",
            "mp3": "https://archive.org/download/gd1985-06-28.141599.aud.bryant.miller.sirmick.flac2496/gd1985-06-28s1t07.mp3"
        },
        {
            "song": "Deal",
            "order": 8,
            "length": 386,
            "ogg": "https://archive.org/download/gd1985-06-28.141599.aud.bryant.miller.sirmick.flac2496/gd1985-06-28s1t08.ogg",
            "mp3": "https://archive.org/download/gd1985-06-28.141599.aud.bryant.miller.sirmick.flac2496/gd1985-06-28s1t08.mp3"
        },
        {
            "song": "tuning",
            "order": 9,
            "length": 411,
            "ogg": "https://archive.org/download/gd1985-06-28.141599.aud.bryant.miller.sirmick.flac2496/gd1985-06-28s1t09.ogg",
            "mp3": "https://archive.org/download/gd1985-06-28.141599.aud.bryant.miller.sirmick.flac2496/gd1985-06-28s1t09.mp3"
        },
        {
            "song": "The Music Never Stopped",
            "order": 10,
            "length": 112,
            "ogg": "https://archive.org/download/gd1985-06-28.141599.aud.bryant.miller.sirmick.flac2496/gd1985-06-28s2t01.ogg",
            "mp3": "https://archive.org/download/gd1985-06-28.141599.aud.bryant.miller.sirmick.flac2496/gd1985-06-28s2t01.mp3"
        },
        {
            "song": "Just Like Tom Thumb's Blues",
            "order": 11,
            "length": 546,
            "ogg": "https://archive.org/download/gd1985-06-28.141599.aud.bryant.miller.sirmick.flac2496/gd1985-06-28s2t02.ogg",
            "mp3": "https://archive.org/download/gd1985-06-28.141599.aud.bryant.miller.sirmick.flac2496/gd1985-06-28s2t02.mp3"
        },
        {
            "song": "Estimated Prophet >",
            "order": 12,
            "length": 311,
            "ogg": "https://archive.org/download/gd1985-06-28.141599.aud.bryant.miller.sirmick.flac2496/gd1985-06-28s2t03.ogg",
            "mp3": "https://archive.org/download/gd1985-06-28.141599.aud.bryant.miller.sirmick.flac2496/gd1985-06-28s2t03.mp3"
        },
        {
            "song": "Terrapin Station >",
            "order": 13,
            "length": 712,
            "ogg": "https://archive.org/download/gd1985-06-28.141599.aud.bryant.miller.sirmick.flac2496/gd1985-06-28s2t04.ogg",
            "mp3": "https://archive.org/download/gd1985-06-28.141599.aud.bryant.miller.sirmick.flac2496/gd1985-06-28s2t04.mp3"
        },
        {
            "song": "Drums >",
            "order": 14,
            "length": 674,
            "ogg": "https://archive.org/download/gd1985-06-28.141599.aud.bryant.miller.sirmick.flac2496/gd1985-06-28s2t05.ogg",
            "mp3": "https://archive.org/download/gd1985-06-28.141599.aud.bryant.miller.sirmick.flac2496/gd1985-06-28s2t05.mp3"
        },
        {
            "song": "Space >",
            "order": 15,
            "length": 706,
            "ogg": "https://archive.org/download/gd1985-06-28.141599.aud.bryant.miller.sirmick.flac2496/gd1985-06-28s2t06.ogg",
            "mp3": "https://archive.org/download/gd1985-06-28.141599.aud.bryant.miller.sirmick.flac2496/gd1985-06-28s2t06.mp3"
        },
        {
            "song": "I Need A Miracle >",
            "order": 16,
            "length": 491,
            "ogg": "https://archive.org/download/gd1985-06-28.141599.aud.bryant.miller.sirmick.flac2496/gd1985-06-28s2t07.ogg",
            "mp3": "https://archive.org/download/gd1985-06-28.141599.aud.bryant.miller.sirmick.flac2496/gd1985-06-28s2t07.mp3"
        },
        {
            "song": "Morning Dew >",
            "order": 17,
            "length": 248,
            "ogg": "https://archive.org/download/gd1985-06-28.141599.aud.bryant.miller.sirmick.flac2496/gd1985-06-28s2t08.ogg",
            "mp3": "https://archive.org/download/gd1985-06-28.141599.aud.bryant.miller.sirmick.flac2496/gd1985-06-28s2t08.mp3"
        },
        {
            "song": "Throwing Stones >",
            "order": 18,
            "length": 651,
            "ogg": "https://archive.org/download/gd1985-06-28.141599.aud.bryant.miller.sirmick.flac2496/gd1985-06-28s2t09.ogg",
            "mp3": "https://archive.org/download/gd1985-06-28.141599.aud.bryant.miller.sirmick.flac2496/gd1985-06-28s2t09.mp3"
        },
        {
            "song": "Not Fade Away",
            "order": 19,
            "length": 541,
            "ogg": "https://archive.org/download/gd1985-06-28.141599.aud.bryant.miller.sirmick.flac2496/gd1985-06-28s2t10.ogg",
            "mp3": "https://archive.org/download/gd1985-06-28.141599.aud.bryant.miller.sirmick.flac2496/gd1985-06-28s2t10.mp3"
        },
        {
            "song": "Keep Your Day Job",
            "order": 20,
            "length": 494,
            "ogg": "https://archive.org/download/gd1985-06-28.141599.aud.bryant.miller.sirmick.flac2496/gd1985-06-28s2t11.ogg",
            "mp3": "https://archive.org/download/gd1985-06-28.141599.aud.bryant.miller.sirmick.flac2496/gd1985-06-28s2t11.mp3"
        },
        {
            "song": "",
            "order": 21,
            "length": 265,
            "ogg": "https://archive.org/download/gd1985-06-28.141599.aud.bryant.miller.sirmick.flac2496/gd1985-06-28s2t12.ogg",
            "mp3": "https://archive.org/download/gd1985-06-28.141599.aud.bryant.miller.sirmick.flac2496/gd1985-06-28s2t12.mp3"
        }
    ]
}