{
    "title": "gd1989-07-10.142467.schoeps.cmc4.mk2s.mattes.miller.clugston.flac1648",
    "venue": "Giants Stadium",
    "year": 1989,
    "month": 7,
    "day": 10,
    "songs": [
        {
            "song": "Crowd",
            "order": 1,
            "length": 294,
            "ogg": "https://archive.org/download/gd1989-07-10.142467.schoeps.cmc4.mk2s.mattes.miller.clugston.flac1648/Gd89-07-10S1t01Crowd.ogg",
            "mp3": "https://archive.org/download/gd1989-07-10.142467.schoeps.cmc4.mk2s.mattes.miller.clugston.flac1648/Gd89-07-10S1t01Crowd.mp3"
        },
        {
            "song": "Feel Like A Stranger",
            "order": 2,
            "length": 436,
            "ogg": "https://archive.org/download/gd1989-07-10.142467.schoeps.cmc4.mk2s.mattes.miller.clugston.flac1648/Gd89-07-10S1t02FeelLikeAStranger.ogg",
            "mp3": "https://archive.org/download/gd1989-07-10.142467.schoeps.cmc4.mk2s.mattes.miller.clugston.flac1648/Gd89-07-10S1t02FeelLikeAStranger.mp3"
        },
        {
            "song": "Franklin's Tower",
            "order": 3,
            "length": 594,
            "ogg": "https://archive.org/download/gd1989-07-10.142467.schoeps.cmc4.mk2s.mattes.miller.clugston.flac1648/Gd89-07-10S1t03FranklinsTower.ogg",
            "mp3": "https://archive.org/download/gd1989-07-10.142467.schoeps.cmc4.mk2s.mattes.miller.clugston.flac1648/Gd89-07-10S1t03FranklinsTower.mp3"
        },
        {
            "song": "Walkin' Blues",
            "order": 4,
            "length": 441,
            "ogg": "https://archive.org/download/gd1989-07-10.142467.schoeps.cmc4.mk2s.mattes.miller.clugston.flac1648/Gd89-07-10S1t04WalkinBlues.ogg",
            "mp3": "https://archive.org/download/gd1989-07-10.142467.schoeps.cmc4.mk2s.mattes.miller.clugston.flac1648/Gd89-07-10S1t04WalkinBlues.mp3"
        },
        {
            "song": "Jack-A-Roe",
            "order": 5,
            "length": 319,
            "ogg": "https://archive.org/download/gd1989-07-10.142467.schoeps.cmc4.mk2s.mattes.miller.clugston.flac1648/Gd89-07-10S1t05Jack-a-roe.ogg",
            "mp3": "https://archive.org/download/gd1989-07-10.142467.schoeps.cmc4.mk2s.mattes.miller.clugston.flac1648/Gd89-07-10S1t05Jack-a-roe.mp3"
        },
        {
            "song": "When I Paint My Masterpiece",
            "order": 6,
            "length": 471,
            "ogg": "https://archive.org/download/gd1989-07-10.142467.schoeps.cmc4.mk2s.mattes.miller.clugston.flac1648/Gd89-07-10S1t06WhenIPaintMyMasterpiece.ogg",
            "mp3": "https://archive.org/download/gd1989-07-10.142467.schoeps.cmc4.mk2s.mattes.miller.clugston.flac1648/Gd89-07-10S1t06WhenIPaintMyMasterpiece.mp3"
        },
        {
            "song": "Tennessee Jed",
            "order": 7,
            "length": 536,
            "ogg": "https://archive.org/download/gd1989-07-10.142467.schoeps.cmc4.mk2s.mattes.miller.clugston.flac1648/Gd89-07-10S1t07TennesseeJed.ogg",
            "mp3": "https://archive.org/download/gd1989-07-10.142467.schoeps.cmc4.mk2s.mattes.miller.clugston.flac1648/Gd89-07-10S1t07TennesseeJed.mp3"
        },
        {
            "song": "The Music Never Stopped",
            "order": 8,
            "length": 378,
            "ogg": "https://archive.org/download/gd1989-07-10.142467.schoeps.cmc4.mk2s.mattes.miller.clugston.flac1648/Gd89-07-10S1t08TheMusicNeverStopped.ogg",
            "mp3": "https://archive.org/download/gd1989-07-10.142467.schoeps.cmc4.mk2s.mattes.miller.clugston.flac1648/Gd89-07-10S1t08TheMusicNeverStopped.mp3"
        },
        {
            "song": "Don't Ease Me In",
            "order": 9,
            "length": 216,
            "ogg": "https://archive.org/download/gd1989-07-10.142467.schoeps.cmc4.mk2s.mattes.miller.clugston.flac1648/Gd89-07-10S1t09DontEaseMeIn.ogg",
            "mp3": "https://archive.org/download/gd1989-07-10.142467.schoeps.cmc4.mk2s.mattes.miller.clugston.flac1648/Gd89-07-10S1t09DontEaseMeIn.mp3"
        },
        {
            "song": "Crowd",
            "order": 10,
            "length": 428,
            "ogg": "https://archive.org/download/gd1989-07-10.142467.schoeps.cmc4.mk2s.mattes.miller.clugston.flac1648/Gd89-07-10S2t01Crowd.ogg",
            "mp3": "https://archive.org/download/gd1989-07-10.142467.schoeps.cmc4.mk2s.mattes.miller.clugston.flac1648/Gd89-07-10S2t01Crowd.mp3"
        },
        {
            "song": "Foolish Heart",
            "order": 11,
            "length": 592,
            "ogg": "https://archive.org/download/gd1989-07-10.142467.schoeps.cmc4.mk2s.mattes.miller.clugston.flac1648/Gd89-07-10S2t02FoolishHeart.ogg",
            "mp3": "https://archive.org/download/gd1989-07-10.142467.schoeps.cmc4.mk2s.mattes.miller.clugston.flac1648/Gd89-07-10S2t02FoolishHeart.mp3"
        },
        {
            "song": "Just A Little Light",
            "order": 12,
            "length": 342,
            "ogg": "https://archive.org/download/gd1989-07-10.142467.schoeps.cmc4.mk2s.mattes.miller.clugston.flac1648/Gd89-07-10S2t03JustALittleLight.ogg",
            "mp3": "https://archive.org/download/gd1989-07-10.142467.schoeps.cmc4.mk2s.mattes.miller.clugston.flac1648/Gd89-07-10S2t03JustALittleLight.mp3"
        },
        {
            "song": "Playin' In The Band",
            "order": 13,
            "length": 401,
            "ogg": "https://archive.org/download/gd1989-07-10.142467.schoeps.cmc4.mk2s.mattes.miller.clugston.flac1648/Gd89-07-10S2t04PlayinInTheBand.ogg",
            "mp3": "https://archive.org/download/gd1989-07-10.142467.schoeps.cmc4.mk2s.mattes.miller.clugston.flac1648/Gd89-07-10S2t04PlayinInTheBand.mp3"
        },
        {
            "song": "Uncle John's Band",
            "order": 14,
            "length": 876,
            "ogg": "https://archive.org/download/gd1989-07-10.142467.schoeps.cmc4.mk2s.mattes.miller.clugston.flac1648/Gd89-07-10S2t05UncleJohnsBand.ogg",
            "mp3": "https://archive.org/download/gd1989-07-10.142467.schoeps.cmc4.mk2s.mattes.miller.clugston.flac1648/Gd89-07-10S2t05UncleJohnsBand.mp3"
        },
        {
            "song": "Drums",
            "order": 15,
            "length": 1082,
            "ogg": "https://archive.org/download/gd1989-07-10.142467.schoeps.cmc4.mk2s.mattes.miller.clugston.flac1648/Gd89-07-10S2t06Drums.ogg",
            "mp3": "https://archive.org/download/gd1989-07-10.142467.schoeps.cmc4.mk2s.mattes.miller.clugston.flac1648/Gd89-07-10S2t06Drums.mp3"
        },
        {
            "song": "Space",
            "order": 16,
            "length": 609,
            "ogg": "https://archive.org/download/gd1989-07-10.142467.schoeps.cmc4.mk2s.mattes.miller.clugston.flac1648/Gd89-07-10S2t07Space.ogg",
            "mp3": "https://archive.org/download/gd1989-07-10.142467.schoeps.cmc4.mk2s.mattes.miller.clugston.flac1648/Gd89-07-10S2t07Space.mp3"
        },
        {
            "song": "Iko Iko",
            "order": 17,
            "length": 490,
            "ogg": "https://archive.org/download/gd1989-07-10.142467.schoeps.cmc4.mk2s.mattes.miller.clugston.flac1648/Gd89-07-10S2t08IkoIko.ogg",
            "mp3": "https://archive.org/download/gd1989-07-10.142467.schoeps.cmc4.mk2s.mattes.miller.clugston.flac1648/Gd89-07-10S2t08IkoIko.mp3"
        },
        {
            "song": "All Along The Watchtower",
            "order": 18,
            "length": 342,
            "ogg": "https://archive.org/download/gd1989-07-10.142467.schoeps.cmc4.mk2s.mattes.miller.clugston.flac1648/Gd89-07-10S2t09AllAlongTheWatchtower.ogg",
            "mp3": "https://archive.org/download/gd1989-07-10.142467.schoeps.cmc4.mk2s.mattes.miller.clugston.flac1648/Gd89-07-10S2t09AllAlongTheWatchtower.mp3"
        },
        {
            "song": "Morning Dew",
            "order": 19,
            "length": 644,
            "ogg": "https://archive.org/download/gd1989-07-10.142467.schoeps.cmc4.mk2s.mattes.miller.clugston.flac1648/Gd89-07-10S2t10MorningDew.ogg",
            "mp3": "https://archive.org/download/gd1989-07-10.142467.schoeps.cmc4.mk2s.mattes.miller.clugston.flac1648/Gd89-07-10S2t10MorningDew.mp3"
        },
        {
            "song": "Sugar Magnolia",
            "order": 20,
            "length": 567,
            "ogg": "https://archive.org/download/gd1989-07-10.142467.schoeps.cmc4.mk2s.mattes.miller.clugston.flac1648/Gd89-07-10S2t11SugarMagnolia.ogg",
            "mp3": "https://archive.org/download/gd1989-07-10.142467.schoeps.cmc4.mk2s.mattes.miller.clugston.flac1648/Gd89-07-10S2t11SugarMagnolia.mp3"
        },
        {
            "song": "Encore Break",
            "order": 21,
            "length": 205,
            "ogg": "https://archive.org/download/gd1989-07-10.142467.schoeps.cmc4.mk2s.mattes.miller.clugston.flac1648/Gd89-07-10S2t12EncoreBreak.ogg",
            "mp3": "https://archive.org/download/gd1989-07-10.142467.schoeps.cmc4.mk2s.mattes.miller.clugston.flac1648/Gd89-07-10S2t12EncoreBreak.mp3"
        },
        {
            "song": "Knockin' On Heaven's Door",
            "order": 22,
            "length": 457,
            "ogg": "https://archive.org/download/gd1989-07-10.142467.schoeps.cmc4.mk2s.mattes.miller.clugston.flac1648/Gd89-07-10S2t13KnockinOnHeavensDoor.ogg",
            "mp3": "https://archive.org/download/gd1989-07-10.142467.schoeps.cmc4.mk2s.mattes.miller.clugston.flac1648/Gd89-07-10S2t13KnockinOnHeavensDoor.mp3"
        }
    ]
}