{
    "title": "gd1990-02-25.fob.akgC568.b-and-d.andrewf.93476.sbeok.flac16",
    "venue": "Oakland-Alameda County Coliseum Arena",
    "year": 1990,
    "month": 2,
    "day": 25,
    "songs": [
        {
            "song": "Touch of Grey >",
            "order": 1,
            "length": 364,
            "ogg": "https://archive.org/download/gd1990-02-25.fob.akgC568.b-and-d.andrewf.93476.sbeok.flac16/gd1990-02-25d1t01.ogg",
            "mp3": "https://archive.org/download/gd1990-02-25.fob.akgC568.b-and-d.andrewf.93476.sbeok.flac16/gd1990-02-25d1t01.mp3"
        },
        {
            "song": "Greatest Story Ever Told",
            "order": 2,
            "length": 299,
            "ogg": "https://archive.org/download/gd1990-02-25.fob.akgC568.b-and-d.andrewf.93476.sbeok.flac16/gd1990-02-25d1t02.ogg",
            "mp3": "https://archive.org/download/gd1990-02-25.fob.akgC568.b-and-d.andrewf.93476.sbeok.flac16/gd1990-02-25d1t02.mp3"
        },
        {
            "song": "Jack-A-Roe",
            "order": 3,
            "length": 399,
            "ogg": "https://archive.org/download/gd1990-02-25.fob.akgC568.b-and-d.andrewf.93476.sbeok.flac16/gd1990-02-25d1t03.ogg",
            "mp3": "https://archive.org/download/gd1990-02-25.fob.akgC568.b-and-d.andrewf.93476.sbeok.flac16/gd1990-02-25d1t03.mp3"
        },
        {
            "song": "Little Red Rooster",
            "order": 4,
            "length": 619,
            "ogg": "https://archive.org/download/gd1990-02-25.fob.akgC568.b-and-d.andrewf.93476.sbeok.flac16/gd1990-02-25d1t04.ogg",
            "mp3": "https://archive.org/download/gd1990-02-25.fob.akgC568.b-and-d.andrewf.93476.sbeok.flac16/gd1990-02-25d1t04.mp3"
        },
        {
            "song": "Stagger Lee",
            "order": 5,
            "length": 397,
            "ogg": "https://archive.org/download/gd1990-02-25.fob.akgC568.b-and-d.andrewf.93476.sbeok.flac16/gd1990-02-25d1t05.ogg",
            "mp3": "https://archive.org/download/gd1990-02-25.fob.akgC568.b-and-d.andrewf.93476.sbeok.flac16/gd1990-02-25d1t05.mp3"
        },
        {
            "song": "Queen Jane Approximately",
            "order": 6,
            "length": 397,
            "ogg": "https://archive.org/download/gd1990-02-25.fob.akgC568.b-and-d.andrewf.93476.sbeok.flac16/gd1990-02-25d1t06.ogg",
            "mp3": "https://archive.org/download/gd1990-02-25.fob.akgC568.b-and-d.andrewf.93476.sbeok.flac16/gd1990-02-25d1t06.mp3"
        },
        {
            "song": "The Last Time",
            "order": 7,
            "length": 330,
            "ogg": "https://archive.org/download/gd1990-02-25.fob.akgC568.b-and-d.andrewf.93476.sbeok.flac16/gd1990-02-25d1t07.ogg",
            "mp3": "https://archive.org/download/gd1990-02-25.fob.akgC568.b-and-d.andrewf.93476.sbeok.flac16/gd1990-02-25d1t07.mp3"
        },
        {
            "song": "tuning",
            "order": 8,
            "length": 186,
            "ogg": "https://archive.org/download/gd1990-02-25.fob.akgC568.b-and-d.andrewf.93476.sbeok.flac16/gd1990-02-25d1t08.ogg",
            "mp3": "https://archive.org/download/gd1990-02-25.fob.akgC568.b-and-d.andrewf.93476.sbeok.flac16/gd1990-02-25d1t08.mp3"
        },
        {
            "song": "Cassidy",
            "order": 9,
            "length": 392,
            "ogg": "https://archive.org/download/gd1990-02-25.fob.akgC568.b-and-d.andrewf.93476.sbeok.flac16/gd1990-02-25d1t09.ogg",
            "mp3": "https://archive.org/download/gd1990-02-25.fob.akgC568.b-and-d.andrewf.93476.sbeok.flac16/gd1990-02-25d1t09.mp3"
        },
        {
            "song": "Deal",
            "order": 10,
            "length": 502,
            "ogg": "https://archive.org/download/gd1990-02-25.fob.akgC568.b-and-d.andrewf.93476.sbeok.flac16/gd1990-02-25d1t10.ogg",
            "mp3": "https://archive.org/download/gd1990-02-25.fob.akgC568.b-and-d.andrewf.93476.sbeok.flac16/gd1990-02-25d1t10.mp3"
        },
        {
            "song": "China Cat Sunflower >",
            "order": 11,
            "length": 360,
            "ogg": "https://archive.org/download/gd1990-02-25.fob.akgC568.b-and-d.andrewf.93476.sbeok.flac16/gd1990-02-25d2t01.ogg",
            "mp3": "https://archive.org/download/gd1990-02-25.fob.akgC568.b-and-d.andrewf.93476.sbeok.flac16/gd1990-02-25d2t01.mp3"
        },
        {
            "song": "I Know You Rider",
            "order": 12,
            "length": 351,
            "ogg": "https://archive.org/download/gd1990-02-25.fob.akgC568.b-and-d.andrewf.93476.sbeok.flac16/gd1990-02-25d2t02.ogg",
            "mp3": "https://archive.org/download/gd1990-02-25.fob.akgC568.b-and-d.andrewf.93476.sbeok.flac16/gd1990-02-25d2t02.mp3"
        },
        {
            "song": "Just a Little Light",
            "order": 13,
            "length": 376,
            "ogg": "https://archive.org/download/gd1990-02-25.fob.akgC568.b-and-d.andrewf.93476.sbeok.flac16/gd1990-02-25d2t03.ogg",
            "mp3": "https://archive.org/download/gd1990-02-25.fob.akgC568.b-and-d.andrewf.93476.sbeok.flac16/gd1990-02-25d2t03.mp3"
        },
        {
            "song": "Estimated Prophet >",
            "order": 14,
            "length": 737,
            "ogg": "https://archive.org/download/gd1990-02-25.fob.akgC568.b-and-d.andrewf.93476.sbeok.flac16/gd1990-02-25d2t04.ogg",
            "mp3": "https://archive.org/download/gd1990-02-25.fob.akgC568.b-and-d.andrewf.93476.sbeok.flac16/gd1990-02-25d2t04.mp3"
        },
        {
            "song": "Eyes of the World >",
            "order": 15,
            "length": 569,
            "ogg": "https://archive.org/download/gd1990-02-25.fob.akgC568.b-and-d.andrewf.93476.sbeok.flac16/gd1990-02-25d2t05.ogg",
            "mp3": "https://archive.org/download/gd1990-02-25.fob.akgC568.b-and-d.andrewf.93476.sbeok.flac16/gd1990-02-25d2t05.mp3"
        },
        {
            "song": "Drums >",
            "order": 16,
            "length": 466,
            "ogg": "https://archive.org/download/gd1990-02-25.fob.akgC568.b-and-d.andrewf.93476.sbeok.flac16/gd1990-02-25d2t06.ogg",
            "mp3": "https://archive.org/download/gd1990-02-25.fob.akgC568.b-and-d.andrewf.93476.sbeok.flac16/gd1990-02-25d2t06.mp3"
        },
        {
            "song": "Space >",
            "order": 17,
            "length": 562,
            "ogg": "https://archive.org/download/gd1990-02-25.fob.akgC568.b-and-d.andrewf.93476.sbeok.flac16/gd1990-02-25d3t01.ogg",
            "mp3": "https://archive.org/download/gd1990-02-25.fob.akgC568.b-and-d.andrewf.93476.sbeok.flac16/gd1990-02-25d3t01.mp3"
        },
        {
            "song": "The Wheel >",
            "order": 18,
            "length": 377,
            "ogg": "https://archive.org/download/gd1990-02-25.fob.akgC568.b-and-d.andrewf.93476.sbeok.flac16/gd1990-02-25d3t02.ogg",
            "mp3": "https://archive.org/download/gd1990-02-25.fob.akgC568.b-and-d.andrewf.93476.sbeok.flac16/gd1990-02-25d3t02.mp3"
        },
        {
            "song": "Gimme Some Lovin' >",
            "order": 19,
            "length": 350,
            "ogg": "https://archive.org/download/gd1990-02-25.fob.akgC568.b-and-d.andrewf.93476.sbeok.flac16/gd1990-02-25d3t03.ogg",
            "mp3": "https://archive.org/download/gd1990-02-25.fob.akgC568.b-and-d.andrewf.93476.sbeok.flac16/gd1990-02-25d3t03.mp3"
        },
        {
            "song": "Wharf Rat >",
            "order": 20,
            "length": 714,
            "ogg": "https://archive.org/download/gd1990-02-25.fob.akgC568.b-and-d.andrewf.93476.sbeok.flac16/gd1990-02-25d3t04.ogg",
            "mp3": "https://archive.org/download/gd1990-02-25.fob.akgC568.b-and-d.andrewf.93476.sbeok.flac16/gd1990-02-25d3t04.mp3"
        },
        {
            "song": "Sugar Magnolia",
            "order": 21,
            "length": 526,
            "ogg": "https://archive.org/download/gd1990-02-25.fob.akgC568.b-and-d.andrewf.93476.sbeok.flac16/gd1990-02-25d3t05.ogg",
            "mp3": "https://archive.org/download/gd1990-02-25.fob.akgC568.b-and-d.andrewf.93476.sbeok.flac16/gd1990-02-25d3t05.mp3"
        },
        {
            "song": "Knockin' on Heaven's Door",
            "order": 22,
            "length": 541,
            "ogg": "https://archive.org/download/gd1990-02-25.fob.akgC568.b-and-d.andrewf.93476.sbeok.flac16/gd1990-02-25d3t06.ogg",
            "mp3": "https://archive.org/download/gd1990-02-25.fob.akgC568.b-and-d.andrewf.93476.sbeok.flac16/gd1990-02-25d3t06.mp3"
        }
    ]
}