{
    "title": "gd1986-12-15.132368.nak300.gidley.flac1644",
    "venue": "Oakland-Alameda County Coliseum",
    "year": 1986,
    "month": 12,
    "day": 15,
    "songs": [
        {
            "song": "crowd",
            "order": 1,
            "length": 64,
            "ogg": "https://archive.org/download/gd1986-12-15.132368.nak300.gidley.flac1644/gd1986-12-15s1t01.ogg",
            "mp3": "https://archive.org/download/gd1986-12-15.132368.nak300.gidley.flac1644/gd1986-12-15s1t01.mp3"
        },
        {
            "song": "Touch of Grey",
            "order": 2,
            "length": 518,
            "ogg": "https://archive.org/download/gd1986-12-15.132368.nak300.gidley.flac1644/gd1986-12-15s1t02.ogg",
            "mp3": "https://archive.org/download/gd1986-12-15.132368.nak300.gidley.flac1644/gd1986-12-15s1t02.mp3"
        },
        {
            "song": "C.C. Rider >",
            "order": 3,
            "length": 465,
            "ogg": "https://archive.org/download/gd1986-12-15.132368.nak300.gidley.flac1644/gd1986-12-15s1t03.ogg",
            "mp3": "https://archive.org/download/gd1986-12-15.132368.nak300.gidley.flac1644/gd1986-12-15s1t03.mp3"
        },
        {
            "song": "When Push Comes to Shove",
            "order": 4,
            "length": 310,
            "ogg": "https://archive.org/download/gd1986-12-15.132368.nak300.gidley.flac1644/gd1986-12-15s1t04.ogg",
            "mp3": "https://archive.org/download/gd1986-12-15.132368.nak300.gidley.flac1644/gd1986-12-15s1t04.mp3"
        },
        {
            "song": "Beat it on Down the Line >",
            "order": 5,
            "length": 184,
            "ogg": "https://archive.org/download/gd1986-12-15.132368.nak300.gidley.flac1644/gd1986-12-15s1t05.ogg",
            "mp3": "https://archive.org/download/gd1986-12-15.132368.nak300.gidley.flac1644/gd1986-12-15s1t05.mp3"
        },
        {
            "song": "Greatest Story Ever Told",
            "order": 6,
            "length": 292,
            "ogg": "https://archive.org/download/gd1986-12-15.132368.nak300.gidley.flac1644/gd1986-12-15s1t06.ogg",
            "mp3": "https://archive.org/download/gd1986-12-15.132368.nak300.gidley.flac1644/gd1986-12-15s1t06.mp3"
        },
        {
            "song": "Loser",
            "order": 7,
            "length": 494,
            "ogg": "https://archive.org/download/gd1986-12-15.132368.nak300.gidley.flac1644/gd1986-12-15s1t07.ogg",
            "mp3": "https://archive.org/download/gd1986-12-15.132368.nak300.gidley.flac1644/gd1986-12-15s1t07.mp3"
        },
        {
            "song": "Cassidy >",
            "order": 8,
            "length": 319,
            "ogg": "https://archive.org/download/gd1986-12-15.132368.nak300.gidley.flac1644/gd1986-12-15s1t08.ogg",
            "mp3": "https://archive.org/download/gd1986-12-15.132368.nak300.gidley.flac1644/gd1986-12-15s1t08.mp3"
        },
        {
            "song": "Althea",
            "order": 9,
            "length": 519,
            "ogg": "https://archive.org/download/gd1986-12-15.132368.nak300.gidley.flac1644/gd1986-12-15s1t09.ogg",
            "mp3": "https://archive.org/download/gd1986-12-15.132368.nak300.gidley.flac1644/gd1986-12-15s1t09.mp3"
        },
        {
            "song": "Brother Esau",
            "order": 10,
            "length": 318,
            "ogg": "https://archive.org/download/gd1986-12-15.132368.nak300.gidley.flac1644/gd1986-12-15s1t10.ogg",
            "mp3": "https://archive.org/download/gd1986-12-15.132368.nak300.gidley.flac1644/gd1986-12-15s1t10.mp3"
        },
        {
            "song": "Candyman",
            "order": 11,
            "length": 392,
            "ogg": "https://archive.org/download/gd1986-12-15.132368.nak300.gidley.flac1644/gd1986-12-15s1t11.ogg",
            "mp3": "https://archive.org/download/gd1986-12-15.132368.nak300.gidley.flac1644/gd1986-12-15s1t11.mp3"
        },
        {
            "song": "Let it Grow",
            "order": 12,
            "length": 649,
            "ogg": "https://archive.org/download/gd1986-12-15.132368.nak300.gidley.flac1644/gd1986-12-15s1t12.ogg",
            "mp3": "https://archive.org/download/gd1986-12-15.132368.nak300.gidley.flac1644/gd1986-12-15s1t12.mp3"
        },
        {
            "song": "crowd",
            "order": 13,
            "length": 45,
            "ogg": "https://archive.org/download/gd1986-12-15.132368.nak300.gidley.flac1644/gd1986-12-15s2t01.ogg",
            "mp3": "https://archive.org/download/gd1986-12-15.132368.nak300.gidley.flac1644/gd1986-12-15s2t01.mp3"
        },
        {
            "song": "Iko Iko >",
            "order": 14,
            "length": 288,
            "ogg": "https://archive.org/download/gd1986-12-15.132368.nak300.gidley.flac1644/gd1986-12-15s2t02.ogg",
            "mp3": "https://archive.org/download/gd1986-12-15.132368.nak300.gidley.flac1644/gd1986-12-15s2t02.mp3"
        },
        {
            "song": "Looks Like Rain",
            "order": 15,
            "length": 527,
            "ogg": "https://archive.org/download/gd1986-12-15.132368.nak300.gidley.flac1644/gd1986-12-15s2t03.ogg",
            "mp3": "https://archive.org/download/gd1986-12-15.132368.nak300.gidley.flac1644/gd1986-12-15s2t03.mp3"
        },
        {
            "song": "Black Muddy River",
            "order": 16,
            "length": 337,
            "ogg": "https://archive.org/download/gd1986-12-15.132368.nak300.gidley.flac1644/gd1986-12-15s2t04.ogg",
            "mp3": "https://archive.org/download/gd1986-12-15.132368.nak300.gidley.flac1644/gd1986-12-15s2t04.mp3"
        },
        {
            "song": "Playin' in the Band >",
            "order": 17,
            "length": 558,
            "ogg": "https://archive.org/download/gd1986-12-15.132368.nak300.gidley.flac1644/gd1986-12-15s2t05.ogg",
            "mp3": "https://archive.org/download/gd1986-12-15.132368.nak300.gidley.flac1644/gd1986-12-15s2t05.mp3"
        },
        {
            "song": "Terrapin >",
            "order": 18,
            "length": 641,
            "ogg": "https://archive.org/download/gd1986-12-15.132368.nak300.gidley.flac1644/gd1986-12-15s2t06.ogg",
            "mp3": "https://archive.org/download/gd1986-12-15.132368.nak300.gidley.flac1644/gd1986-12-15s2t06.mp3"
        },
        {
            "song": "Drums >",
            "order": 19,
            "length": 600,
            "ogg": "https://archive.org/download/gd1986-12-15.132368.nak300.gidley.flac1644/gd1986-12-15s2t07.ogg",
            "mp3": "https://archive.org/download/gd1986-12-15.132368.nak300.gidley.flac1644/gd1986-12-15s2t07.mp3"
        },
        {
            "song": "Space >",
            "order": 20,
            "length": 639,
            "ogg": "https://archive.org/download/gd1986-12-15.132368.nak300.gidley.flac1644/gd1986-12-15s2t08.ogg",
            "mp3": "https://archive.org/download/gd1986-12-15.132368.nak300.gidley.flac1644/gd1986-12-15s2t08.mp3"
        },
        {
            "song": "Truckin' >",
            "order": 21,
            "length": 382,
            "ogg": "https://archive.org/download/gd1986-12-15.132368.nak300.gidley.flac1644/gd1986-12-15s2t09.ogg",
            "mp3": "https://archive.org/download/gd1986-12-15.132368.nak300.gidley.flac1644/gd1986-12-15s2t09.mp3"
        },
        {
            "song": "Wharf Rat >",
            "order": 22,
            "length": 508,
            "ogg": "https://archive.org/download/gd1986-12-15.132368.nak300.gidley.flac1644/gd1986-12-15s2t10.ogg",
            "mp3": "https://archive.org/download/gd1986-12-15.132368.nak300.gidley.flac1644/gd1986-12-15s2t10.mp3"
        },
        {
            "song": "Playin' Reprise",
            "order": 23,
            "length": 273,
            "ogg": "https://archive.org/download/gd1986-12-15.132368.nak300.gidley.flac1644/gd1986-12-15s2t11.ogg",
            "mp3": "https://archive.org/download/gd1986-12-15.132368.nak300.gidley.flac1644/gd1986-12-15s2t11.mp3"
        },
        {
            "song": "Good Lovin'",
            "order": 24,
            "length": 494,
            "ogg": "https://archive.org/download/gd1986-12-15.132368.nak300.gidley.flac1644/gd1986-12-15s2t12.ogg",
            "mp3": "https://archive.org/download/gd1986-12-15.132368.nak300.gidley.flac1644/gd1986-12-15s2t12.mp3"
        },
        {
            "song": "Encore: Johnny B. Goode",
            "order": 25,
            "length": 260,
            "ogg": "https://archive.org/download/gd1986-12-15.132368.nak300.gidley.flac1644/gd1986-12-15s2t13.ogg",
            "mp3": "https://archive.org/download/gd1986-12-15.132368.nak300.gidley.flac1644/gd1986-12-15s2t13.mp3"
        }
    ]
}