{
    "title": "gd1990-07-14.141748.FOB.MTX.photoLeon.t-flac1644",
    "venue": "Foxboro Stadium",
    "year": 1990,
    "month": 7,
    "day": 14,
    "songs": [
        {
            "song": "crowd - tuning",
            "order": 1,
            "length": 195,
            "ogg": "https://archive.org/download/gd1990-07-14.141748.FOB.MTX.photoLeon.t-flac1644/gd90-07-14.s1t01.ogg",
            "mp3": "https://archive.org/download/gd1990-07-14.141748.FOB.MTX.photoLeon.t-flac1644/gd90-07-14.s1t01.mp3"
        },
        {
            "song": "Shakedown Street ->",
            "order": 2,
            "length": 763,
            "ogg": "https://archive.org/download/gd1990-07-14.141748.FOB.MTX.photoLeon.t-flac1644/gd90-07-14.s1t02.ogg",
            "mp3": "https://archive.org/download/gd1990-07-14.141748.FOB.MTX.photoLeon.t-flac1644/gd90-07-14.s1t02.mp3"
        },
        {
            "song": "Walkin' Blues",
            "order": 3,
            "length": 425,
            "ogg": "https://archive.org/download/gd1990-07-14.141748.FOB.MTX.photoLeon.t-flac1644/gd90-07-14.s1t03.ogg",
            "mp3": "https://archive.org/download/gd1990-07-14.141748.FOB.MTX.photoLeon.t-flac1644/gd90-07-14.s1t03.mp3"
        },
        {
            "song": "Far From Me",
            "order": 4,
            "length": 471,
            "ogg": "https://archive.org/download/gd1990-07-14.141748.FOB.MTX.photoLeon.t-flac1644/gd90-07-14.s1t04.ogg",
            "mp3": "https://archive.org/download/gd1990-07-14.141748.FOB.MTX.photoLeon.t-flac1644/gd90-07-14.s1t04.mp3"
        },
        {
            "song": "Candyman",
            "order": 5,
            "length": 477,
            "ogg": "https://archive.org/download/gd1990-07-14.141748.FOB.MTX.photoLeon.t-flac1644/gd90-07-14.s1t05.ogg",
            "mp3": "https://archive.org/download/gd1990-07-14.141748.FOB.MTX.photoLeon.t-flac1644/gd90-07-14.s1t05.mp3"
        },
        {
            "song": "Stuck Inside of Mobile with The Memphis Blues Again",
            "order": 6,
            "length": 525,
            "ogg": "https://archive.org/download/gd1990-07-14.141748.FOB.MTX.photoLeon.t-flac1644/gd90-07-14.s1t06.ogg",
            "mp3": "https://archive.org/download/gd1990-07-14.141748.FOB.MTX.photoLeon.t-flac1644/gd90-07-14.s1t06.mp3"
        },
        {
            "song": "tuning",
            "order": 7,
            "length": 131,
            "ogg": "https://archive.org/download/gd1990-07-14.141748.FOB.MTX.photoLeon.t-flac1644/gd90-07-14.s1t07.ogg",
            "mp3": "https://archive.org/download/gd1990-07-14.141748.FOB.MTX.photoLeon.t-flac1644/gd90-07-14.s1t07.mp3"
        },
        {
            "song": "Ramble On Rose",
            "order": 8,
            "length": 552,
            "ogg": "https://archive.org/download/gd1990-07-14.141748.FOB.MTX.photoLeon.t-flac1644/gd90-07-14.s1t08.ogg",
            "mp3": "https://archive.org/download/gd1990-07-14.141748.FOB.MTX.photoLeon.t-flac1644/gd90-07-14.s1t08.mp3"
        },
        {
            "song": "One More Saturday Night",
            "order": 9,
            "length": 307,
            "ogg": "https://archive.org/download/gd1990-07-14.141748.FOB.MTX.photoLeon.t-flac1644/gd90-07-14.s1t09.ogg",
            "mp3": "https://archive.org/download/gd1990-07-14.141748.FOB.MTX.photoLeon.t-flac1644/gd90-07-14.s1t09.mp3"
        },
        {
            "song": "Take a Step Back",
            "order": 10,
            "length": 223,
            "ogg": "https://archive.org/download/gd1990-07-14.141748.FOB.MTX.photoLeon.t-flac1644/gd90-07-14.s2t01.ogg",
            "mp3": "https://archive.org/download/gd1990-07-14.141748.FOB.MTX.photoLeon.t-flac1644/gd90-07-14.s2t01.mp3"
        },
        {
            "song": "Eyes of The World ->",
            "order": 11,
            "length": 843,
            "ogg": "https://archive.org/download/gd1990-07-14.141748.FOB.MTX.photoLeon.t-flac1644/gd90-07-14.s2t02.ogg",
            "mp3": "https://archive.org/download/gd1990-07-14.141748.FOB.MTX.photoLeon.t-flac1644/gd90-07-14.s2t02.mp3"
        },
        {
            "song": "Estimated Prophet ->",
            "order": 12,
            "length": 718,
            "ogg": "https://archive.org/download/gd1990-07-14.141748.FOB.MTX.photoLeon.t-flac1644/gd90-07-14.s2t03.ogg",
            "mp3": "https://archive.org/download/gd1990-07-14.141748.FOB.MTX.photoLeon.t-flac1644/gd90-07-14.s2t03.mp3"
        },
        {
            "song": "Crazy Fingers ->",
            "order": 13,
            "length": 472,
            "ogg": "https://archive.org/download/gd1990-07-14.141748.FOB.MTX.photoLeon.t-flac1644/gd90-07-14.s2t04.ogg",
            "mp3": "https://archive.org/download/gd1990-07-14.141748.FOB.MTX.photoLeon.t-flac1644/gd90-07-14.s2t04.mp3"
        },
        {
            "song": "Uncle John's Band ->",
            "order": 14,
            "length": 559,
            "ogg": "https://archive.org/download/gd1990-07-14.141748.FOB.MTX.photoLeon.t-flac1644/gd90-07-14.s2t05.ogg",
            "mp3": "https://archive.org/download/gd1990-07-14.141748.FOB.MTX.photoLeon.t-flac1644/gd90-07-14.s2t05.mp3"
        },
        {
            "song": "Drums ->",
            "order": 15,
            "length": 614,
            "ogg": "https://archive.org/download/gd1990-07-14.141748.FOB.MTX.photoLeon.t-flac1644/gd90-07-14.s2t06.ogg",
            "mp3": "https://archive.org/download/gd1990-07-14.141748.FOB.MTX.photoLeon.t-flac1644/gd90-07-14.s2t06.mp3"
        },
        {
            "song": "Space ->",
            "order": 16,
            "length": 552,
            "ogg": "https://archive.org/download/gd1990-07-14.141748.FOB.MTX.photoLeon.t-flac1644/gd90-07-14.s2t07.ogg",
            "mp3": "https://archive.org/download/gd1990-07-14.141748.FOB.MTX.photoLeon.t-flac1644/gd90-07-14.s2t07.mp3"
        },
        {
            "song": "I Will Take You Home ->",
            "order": 17,
            "length": 280,
            "ogg": "https://archive.org/download/gd1990-07-14.141748.FOB.MTX.photoLeon.t-flac1644/gd90-07-14.s2t08.ogg",
            "mp3": "https://archive.org/download/gd1990-07-14.141748.FOB.MTX.photoLeon.t-flac1644/gd90-07-14.s2t08.mp3"
        },
        {
            "song": "I Need a Miracle ->",
            "order": 18,
            "length": 287,
            "ogg": "https://archive.org/download/gd1990-07-14.141748.FOB.MTX.photoLeon.t-flac1644/gd90-07-14.s2t09.ogg",
            "mp3": "https://archive.org/download/gd1990-07-14.141748.FOB.MTX.photoLeon.t-flac1644/gd90-07-14.s2t09.mp3"
        },
        {
            "song": "Goin' Down The Road Feeling Bad ->",
            "order": 19,
            "length": 416,
            "ogg": "https://archive.org/download/gd1990-07-14.141748.FOB.MTX.photoLeon.t-flac1644/gd90-07-14.s2t10.ogg",
            "mp3": "https://archive.org/download/gd1990-07-14.141748.FOB.MTX.photoLeon.t-flac1644/gd90-07-14.s2t10.mp3"
        },
        {
            "song": "Throwing Stones ->",
            "order": 20,
            "length": 578,
            "ogg": "https://archive.org/download/gd1990-07-14.141748.FOB.MTX.photoLeon.t-flac1644/gd90-07-14.s2t11.ogg",
            "mp3": "https://archive.org/download/gd1990-07-14.141748.FOB.MTX.photoLeon.t-flac1644/gd90-07-14.s2t11.mp3"
        },
        {
            "song": "Turn On Your Love Light",
            "order": 21,
            "length": 396,
            "ogg": "https://archive.org/download/gd1990-07-14.141748.FOB.MTX.photoLeon.t-flac1644/gd90-07-14.s2t12.ogg",
            "mp3": "https://archive.org/download/gd1990-07-14.141748.FOB.MTX.photoLeon.t-flac1644/gd90-07-14.s2t12.mp3"
        },
        {
            "song": "encore break",
            "order": 22,
            "length": 121,
            "ogg": "https://archive.org/download/gd1990-07-14.141748.FOB.MTX.photoLeon.t-flac1644/gd90-07-14.s2t13.ogg",
            "mp3": "https://archive.org/download/gd1990-07-14.141748.FOB.MTX.photoLeon.t-flac1644/gd90-07-14.s2t13.mp3"
        },
        {
            "song": "The Last Time ->",
            "order": 23,
            "length": 375,
            "ogg": "https://archive.org/download/gd1990-07-14.141748.FOB.MTX.photoLeon.t-flac1644/gd90-07-14.s2t14.ogg",
            "mp3": "https://archive.org/download/gd1990-07-14.141748.FOB.MTX.photoLeon.t-flac1644/gd90-07-14.s2t14.mp3"
        },
        {
            "song": "We Bid You Good Night",
            "order": 24,
            "length": 195,
            "ogg": "https://archive.org/download/gd1990-07-14.141748.FOB.MTX.photoLeon.t-flac1644/gd90-07-14.s2t15.ogg",
            "mp3": "https://archive.org/download/gd1990-07-14.141748.FOB.MTX.photoLeon.t-flac1644/gd90-07-14.s2t15.mp3"
        }
    ]
}