{
    "year": 1984,
    "month": 4,
    "day": 7,
    "venue": {
        "venue": "Irvine Meadows Amphitheatre",
        "city": "Irvine",
        "state": "CA",
        "country": "US"
    },
    "sets": [
        {
            "songs": [
                {
                    "name": "Feel Like A Stranger",
                    "length": "7m 58s",
                    "transition": false
                },
                {
                    "name": "West L.A. Fadeaway",
                    "length": "9m 36s",
                    "transition": false
                },
                {
                    "name": "Me & My Uncle",
                    "length": "3m 30s",
                    "transition": false
                },
                {
                    "name": "Mexicali Blues",
                    "length": "6m 28s",
                    "transition": false
                },
                {
                    "name": "Althea",
                    "length": "7m 56s",
                    "transition": false
                },
                {
                    "name": "C.C. Rider",
                    "length": "Unknown",
                    "transition": false
                },
                {
                    "name": "Big Railroad Blues",
                    "length": "4m 13s",
                    "transition": false
                },
                {
                    "name": "Brother Esau",
                    "length": "5m 23s",
                    "transition": false
                },
                {
                    "name": "Touch Of Gray",
                    "length": "7m 16s",
                    "transition": false
                }
            ]
        },
        {
            "songs": [
                {
                    "name": "Iko Iko",
                    "length": "7m 42s",
                    "transition": false
                },
                {
                    "name": "Playin' In The Band",
                    "length": "10m 40s",
                    "transition": false
                },
                {
                    "name": "Uncle John's Band",
                    "length": "13m 40s",
                    "transition": false
                },
                {
                    "name": "Drums",
                    "length": "9m 4s",
                    "transition": false
                },
                {
                    "name": "Spanish Jam",
                    "length": "4m 51s",
                    "transition": false
                },
                {
                    "name": "The Other One",
                    "length": "5m 26s",
                    "transition": false
                },
                {
                    "name": "Throwing Stones",
                    "length": "8m 53s",
                    "transition": false
                },
                {
                    "name": "Wharf Rat",
                    "length": "8m 20s",
                    "transition": false
                },
                {
                    "name": "Not Fade Away",
                    "length": "10m 34s",
                    "transition": false
                }
            ]
        },
        {
            "songs": [
                {
                    "name": "Not Fade Away",
                    "length": "1m 12s",
                    "transition": false
                },
                {
                    "name": "One More Saturday Night",
                    "length": "4m 21s",
                    "transition": false
                }
            ]
        }
    ]
}